odoo/addons/document_page/README.rst
odoo/addons/document_page/__init__.py
odoo/addons/document_page/__manifest__.py
odoo/addons/document_page/demo/document_page.xml
odoo/addons/document_page/i18n/am.po
odoo/addons/document_page/i18n/ar.po
odoo/addons/document_page/i18n/bg.po
odoo/addons/document_page/i18n/bs.po
odoo/addons/document_page/i18n/ca.po
odoo/addons/document_page/i18n/cs.po
odoo/addons/document_page/i18n/da.po
odoo/addons/document_page/i18n/de.po
odoo/addons/document_page/i18n/document_page.pot
odoo/addons/document_page/i18n/el.po
odoo/addons/document_page/i18n/el_GR.po
odoo/addons/document_page/i18n/en.po
odoo/addons/document_page/i18n/en_AU.po
odoo/addons/document_page/i18n/en_GB.po
odoo/addons/document_page/i18n/es.po
odoo/addons/document_page/i18n/es_AR.po
odoo/addons/document_page/i18n/es_CL.po
odoo/addons/document_page/i18n/es_CO.po
odoo/addons/document_page/i18n/es_CR.po
odoo/addons/document_page/i18n/es_DO.po
odoo/addons/document_page/i18n/es_EC.po
odoo/addons/document_page/i18n/es_ES.po
odoo/addons/document_page/i18n/es_MX.po
odoo/addons/document_page/i18n/es_PY.po
odoo/addons/document_page/i18n/es_VE.po
odoo/addons/document_page/i18n/et.po
odoo/addons/document_page/i18n/eu.po
odoo/addons/document_page/i18n/fa.po
odoo/addons/document_page/i18n/fi.po
odoo/addons/document_page/i18n/fr.po
odoo/addons/document_page/i18n/fr_CA.po
odoo/addons/document_page/i18n/gl.po
odoo/addons/document_page/i18n/gu.po
odoo/addons/document_page/i18n/he.po
odoo/addons/document_page/i18n/hi.po
odoo/addons/document_page/i18n/hr.po
odoo/addons/document_page/i18n/hu.po
odoo/addons/document_page/i18n/hy.po
odoo/addons/document_page/i18n/id.po
odoo/addons/document_page/i18n/is.po
odoo/addons/document_page/i18n/it.po
odoo/addons/document_page/i18n/ja.po
odoo/addons/document_page/i18n/ka.po
odoo/addons/document_page/i18n/kab.po
odoo/addons/document_page/i18n/kk.po
odoo/addons/document_page/i18n/ko.po
odoo/addons/document_page/i18n/ln.po
odoo/addons/document_page/i18n/lo.po
odoo12_addon_document_page-12.0.1.3.0.dist-info/METADATA
odoo12_addon_document_page-12.0.1.3.0.dist-info/WHEEL
odoo12_addon_document_page-12.0.1.3.0.dist-info/top_level.txt
odoo12_addon_document_page-12.0.1.3.0.dist-info/RECORD
